<?xml version="1.0" encoding="utf-8" standalone="yes"?>
<TrackInfo>
  <Track>
    <FloorName>StartFloor</FloorName>
    <TrackNumber>0</TrackNumber>
    <FloorNumber>-1</FloorNumber>
    <X>3.747653</X>
    <Y>2</Y>
    <Z>3.337047</Z>
  </Track>
  <Track>
    <FloorName>MiddleFloor</FloorName>
    <TrackNumber>0</TrackNumber>
    <FloorNumber>0</FloorNumber>
    <X>5.79504</X>
    <Y>2</Y>
    <Z>6.726485</Z>
  </Track>
  <Track>
    <FloorName>MiddleFloor</FloorName>
    <TrackNumber>0</TrackNumber>
    <FloorNumber>1</FloorNumber>
    <X>6.258408</X>
    <Y>2</Y>
    <Z>10.93184</Z>
  </Track>
  <Track>
    <FloorName>MiddleFloor</FloorName>
    <TrackNumber>0</TrackNumber>
    <FloorNumber>2</FloorNumber>
    <X>6.231063</X>
    <Y>2</Y>
    <Z>18.13193</Z>
  </Track>
  <Track>
    <FloorName>MiddleFloor</FloorName>
    <TrackNumber>0</TrackNumber>
    <FloorNumber>3</FloorNumber>
    <X>6.608373</X>
    <Y>2</Y>
    <Z>20.53574</Z>
  </Track>
  <Track>
    <FloorName>MiddleFloor</FloorName>
    <TrackNumber>0</TrackNumber>
    <FloorNumber>4</FloorNumber>
    <X>7.998451</X>
    <Y>2</Y>
    <Z>22.77606</Z>
  </Track>
  <Track>
    <FloorName>MiddleFloor</FloorName>
    <TrackNumber>0</TrackNumber>
    <FloorNumber>5</FloorNumber>
    <X>10.18803</X>
    <Y>2</Y>
    <Z>24.45654</Z>
  </Track>
  <Track>
    <FloorName>MiddleFloor</FloorName>
    <TrackNumber>0</TrackNumber>
    <FloorNumber>6</FloorNumber>
    <X>12.49441</X>
    <Y>2</Y>
    <Z>25.21995</Z>
  </Track>
  <Track>
    <FloorName>MiddleFloor</FloorName>
    <TrackNumber>0</TrackNumber>
    <FloorNumber>7</FloorNumber>
    <X>18.35071</X>
    <Y>2</Y>
    <Z>25.25254</Z>
  </Track>
  <Track>
    <FloorName>MiddleFloor</FloorName>
    <TrackNumber>0</TrackNumber>
    <FloorNumber>8</FloorNumber>
    <X>20.82312</X>
    <Y>2</Y>
    <Z>23.96616</Z>
  </Track>
  <Track>
    <FloorName>MiddleFloor</FloorName>
    <TrackNumber>0</TrackNumber>
    <FloorNumber>9</FloorNumber>
    <X>21.99177</X>
    <Y>2</Y>
    <Z>21.85473</Z>
  </Track>
  <Track>
    <FloorName>MiddleFloor</FloorName>
    <TrackNumber>0</TrackNumber>
    <FloorNumber>10</FloorNumber>
    <X>22.23063</X>
    <Y>2</Y>
    <Z>19.52431</Z>
  </Track>
  <Track>
    <FloorName>MiddleFloor</FloorName>
    <TrackNumber>0</TrackNumber>
    <FloorNumber>11</FloorNumber>
    <X>21.62817</X>
    <Y>2</Y>
    <Z>17.32386</Z>
  </Track>
  <Track>
    <FloorName>MiddleFloor</FloorName>
    <TrackNumber>0</TrackNumber>
    <FloorNumber>12</FloorNumber>
    <X>20.08001</X>
    <Y>2</Y>
    <Z>15.87917</Z>
  </Track>
  <Track>
    <FloorName>MiddleFloor</FloorName>
    <TrackNumber>0</TrackNumber>
    <FloorNumber>13</FloorNumber>
    <X>18.0927</X>
    <Y>2</Y>
    <Z>15.11952</Z>
  </Track>
  <Track>
    <FloorName>MiddleFloor</FloorName>
    <TrackNumber>0</TrackNumber>
    <FloorNumber>14</FloorNumber>
    <X>15.23457</X>
    <Y>2</Y>
    <Z>15.1314</Z>
  </Track>
  <Track>
    <FloorName>MiddleFloor</FloorName>
    <TrackNumber>0</TrackNumber>
    <FloorNumber>15</FloorNumber>
    <X>13.46108</X>
    <Y>2</Y>
    <Z>14.53549</Z>
  </Track>
  <Track>
    <FloorName>MiddleFloor</FloorName>
    <TrackNumber>0</TrackNumber>
    <FloorNumber>16</FloorNumber>
    <X>12.20294</X>
    <Y>2</Y>
    <Z>12.76034</Z>
  </Track>
  <Track>
    <FloorName>MiddleFloor</FloorName>
    <TrackNumber>0</TrackNumber>
    <FloorNumber>17</FloorNumber>
    <X>11.84017</X>
    <Y>2</Y>
    <Z>11.06257</Z>
  </Track>
  <Track>
    <FloorName>MiddleFloor</FloorName>
    <TrackNumber>0</TrackNumber>
    <FloorNumber>18</FloorNumber>
    <X>11.74431</X>
    <Y>2</Y>
    <Z>4.607786</Z>
  </Track>
  <Track>
    <FloorName>MiddleFloor</FloorName>
    <TrackNumber>0</TrackNumber>
    <FloorNumber>19</FloorNumber>
    <X>12.66529</X>
    <Y>2</Y>
    <Z>3.12427</Z>
  </Track>
  <Track>
    <FloorName>MiddleFloor</FloorName>
    <TrackNumber>0</TrackNumber>
    <FloorNumber>20</FloorNumber>
    <X>14.29013</X>
    <Y>2</Y>
    <Z>2.659517</Z>
  </Track>
  <Track>
    <FloorName>MiddleFloor</FloorName>
    <TrackNumber>0</TrackNumber>
    <FloorNumber>21</FloorNumber>
    <X>15.94219</X>
    <Y>2</Y>
    <Z>2.814016</Z>
  </Track>
  <Track>
    <FloorName>MiddleFloor</FloorName>
    <TrackNumber>0</TrackNumber>
    <FloorNumber>22</FloorNumber>
    <X>17.38693</X>
    <Y>2</Y>
    <Z>3.858539</Z>
  </Track>
  <Track>
    <FloorName>MiddleFloor</FloorName>
    <TrackNumber>0</TrackNumber>
    <FloorNumber>23</FloorNumber>
    <X>18.14786</X>
    <Y>2</Y>
    <Z>5.429727</Z>
  </Track>
  <Track>
    <FloorName>MiddleFloor</FloorName>
    <TrackNumber>0</TrackNumber>
    <FloorNumber>24</FloorNumber>
    <X>19.15333</X>
    <Y>2</Y>
    <Z>7.103847</Z>
  </Track>
  <Track>
    <FloorName>MiddleFloor</FloorName>
    <TrackNumber>0</TrackNumber>
    <FloorNumber>25</FloorNumber>
    <X>20.38327</X>
    <Y>2</Y>
    <Z>8.596313</Z>
  </Track>
  <Track>
    <FloorName>MiddleFloor</FloorName>
    <TrackNumber>0</TrackNumber>
    <FloorNumber>26</FloorNumber>
    <X>21.91013</X>
    <Y>2</Y>
    <Z>9.768277</Z>
  </Track>
  <Track>
    <FloorName>MiddleFloor</FloorName>
    <TrackNumber>0</TrackNumber>
    <FloorNumber>27</FloorNumber>
    <X>23.521</X>
    <Y>2</Y>
    <Z>10.63928</Z>
  </Track>
  <Track>
    <FloorName>MiddleFloor</FloorName>
    <TrackNumber>0</TrackNumber>
    <FloorNumber>28</FloorNumber>
    <X>25.34827</X>
    <Y>2</Y>
    <Z>11.1904</Z>
  </Track>
  <Track>
    <FloorName>EndFloor</FloorName>
    <TrackNumber>0</TrackNumber>
    <FloorNumber>-1</FloorNumber>
    <X>27.09141</X>
    <Y>2</Y>
    <Z>11.38531</Z>
  </Track>
  <Track>
    <FloorName>StartFloor</FloorName>
    <TrackNumber>1</TrackNumber>
    <FloorNumber>-1</FloorNumber>
    <X>27.14458</X>
    <Y>2</Y>
    <Z>11.35253</Z>
  </Track>
  <Track>
    <FloorName>MiddleFloor</FloorName>
    <TrackNumber>1</TrackNumber>
    <FloorNumber>0</FloorNumber>
    <X>25.34827</X>
    <Y>2</Y>
    <Z>11.1904</Z>
  </Track>
  <Track>
    <FloorName>MiddleFloor</FloorName>
    <TrackNumber>1</TrackNumber>
    <FloorNumber>1</FloorNumber>
    <X>23.56692</X>
    <Y>2</Y>
    <Z>10.65191</Z>
  </Track>
  <Track>
    <FloorName>MiddleFloor</FloorName>
    <TrackNumber>1</TrackNumber>
    <FloorNumber>2</FloorNumber>
    <X>21.87409</X>
    <Y>2</Y>
    <Z>9.711092</Z>
  </Track>
  <Track>
    <FloorName>MiddleFloor</FloorName>
    <TrackNumber>1</TrackNumber>
    <FloorNumber>3</FloorNumber>
    <X>20.38327</X>
    <Y>2</Y>
    <Z>8.596313</Z>
  </Track>
  <Track>
    <FloorName>MiddleFloor</FloorName>
    <TrackNumber>1</TrackNumber>
    <FloorNumber>4</FloorNumber>
    <X>19.15333</X>
    <Y>2</Y>
    <Z>7.103847</Z>
  </Track>
  <Track>
    <FloorName>MiddleFloor</FloorName>
    <TrackNumber>1</TrackNumber>
    <FloorNumber>5</FloorNumber>
    <X>18.14786</X>
    <Y>2</Y>
    <Z>5.429727</Z>
  </Track>
  <Track>
    <FloorName>MiddleFloor</FloorName>
    <TrackNumber>1</TrackNumber>
    <FloorNumber>6</FloorNumber>
    <X>17.34317</X>
    <Y>2</Y>
    <Z>3.846466</Z>
  </Track>
  <Track>
    <FloorName>MiddleFloor</FloorName>
    <TrackNumber>1</TrackNumber>
    <FloorNumber>7</FloorNumber>
    <X>15.98572</X>
    <Y>2</Y>
    <Z>2.826016</Z>
  </Track>
  <Track>
    <FloorName>MiddleFloor</FloorName>
    <TrackNumber>1</TrackNumber>
    <FloorNumber>8</FloorNumber>
    <X>14.23418</X>
    <Y>2</Y>
    <Z>2.687201</Z>
  </Track>
  <Track>
    <FloorName>MiddleFloor</FloorName>
    <TrackNumber>1</TrackNumber>
    <FloorNumber>9</FloorNumber>
    <X>12.57726</X>
    <Y>2</Y>
    <Z>3.100038</Z>
  </Track>
  <Track>
    <FloorName>MiddleFloor</FloorName>
    <TrackNumber>1</TrackNumber>
    <FloorNumber>10</FloorNumber>
    <X>11.71326</X>
    <Y>2</Y>
    <Z>4.553994</Z>
  </Track>
  <Track>
    <FloorName>MiddleFloor</FloorName>
    <TrackNumber>1</TrackNumber>
    <FloorNumber>11</FloorNumber>
    <X>11.85868</X>
    <Y>2</Y>
    <Z>11.16944</Z>
  </Track>
  <Track>
    <FloorName>MiddleFloor</FloorName>
    <TrackNumber>1</TrackNumber>
    <FloorNumber>12</FloorNumber>
    <X>12.20752</X>
    <Y>2</Y>
    <Z>12.91862</Z>
  </Track>
  <Track>
    <FloorName>MiddleFloor</FloorName>
    <TrackNumber>1</TrackNumber>
    <FloorNumber>13</FloorNumber>
    <X>13.36376</X>
    <Y>2</Y>
    <Z>14.50871</Z>
  </Track>
  <Track>
    <FloorName>MiddleFloor</FloorName>
    <TrackNumber>1</TrackNumber>
    <FloorNumber>14</FloorNumber>
    <X>15.04835</X>
    <Y>2</Y>
    <Z>15.24128</Z>
  </Track>
  <Track>
    <FloorName>MiddleFloor</FloorName>
    <TrackNumber>1</TrackNumber>
    <FloorNumber>15</FloorNumber>
    <X>18.1776</X>
    <Y>2</Y>
    <Z>15.19586</Z>
  </Track>
  <Track>
    <FloorName>MiddleFloor</FloorName>
    <TrackNumber>1</TrackNumber>
    <FloorNumber>16</FloorNumber>
    <X>20.06896</X>
    <Y>2</Y>
    <Z>15.92927</Z>
  </Track>
  <Track>
    <FloorName>MiddleFloor</FloorName>
    <TrackNumber>1</TrackNumber>
    <FloorNumber>17</FloorNumber>
    <X>21.59689</X>
    <Y>2</Y>
    <Z>17.47761</Z>
  </Track>
  <Track>
    <FloorName>MiddleFloor</FloorName>
    <TrackNumber>1</TrackNumber>
    <FloorNumber>18</FloorNumber>
    <X>22.14984</X>
    <Y>2</Y>
    <Z>19.67012</Z>
  </Track>
  <Track>
    <FloorName>MiddleFloor</FloorName>
    <TrackNumber>1</TrackNumber>
    <FloorNumber>19</FloorNumber>
    <X>22.06136</X>
    <Y>2</Y>
    <Z>22.04877</Z>
  </Track>
  <Track>
    <FloorName>MiddleFloor</FloorName>
    <TrackNumber>1</TrackNumber>
    <FloorNumber>20</FloorNumber>
    <X>20.89245</X>
    <Y>2</Y>
    <Z>24.16712</Z>
  </Track>
  <Track>
    <FloorName>MiddleFloor</FloorName>
    <TrackNumber>1</TrackNumber>
    <FloorNumber>21</FloorNumber>
    <X>18.5736</X>
    <Y>2</Y>
    <Z>25.25153</Z>
  </Track>
  <Track>
    <FloorName>MiddleFloor</FloorName>
    <TrackNumber>1</TrackNumber>
    <FloorNumber>22</FloorNumber>
    <X>12.42529</X>
    <Y>2</Y>
    <Z>25.26497</Z>
  </Track>
  <Track>
    <FloorName>MiddleFloor</FloorName>
    <TrackNumber>1</TrackNumber>
    <FloorNumber>23</FloorNumber>
    <X>10.20714</X>
    <Y>2</Y>
    <Z>24.58974</Z>
  </Track>
  <Track>
    <FloorName>MiddleFloor</FloorName>
    <TrackNumber>1</TrackNumber>
    <FloorNumber>24</FloorNumber>
    <X>7.997225</X>
    <Y>2</Y>
    <Z>22.9645</Z>
  </Track>
  <Track>
    <FloorName>MiddleFloor</FloorName>
    <TrackNumber>1</TrackNumber>
    <FloorNumber>25</FloorNumber>
    <X>6.693873</X>
    <Y>2</Y>
    <Z>20.62034</Z>
  </Track>
  <Track>
    <FloorName>MiddleFloor</FloorName>
    <TrackNumber>1</TrackNumber>
    <FloorNumber>26</FloorNumber>
    <X>6.15438</X>
    <Y>2</Y>
    <Z>18.19342</Z>
  </Track>
  <Track>
    <FloorName>MiddleFloor</FloorName>
    <TrackNumber>1</TrackNumber>
    <FloorNumber>27</FloorNumber>
    <X>6.133899</X>
    <Y>2</Y>
    <Z>10.98372</Z>
  </Track>
  <Track>
    <FloorName>MiddleFloor</FloorName>
    <TrackNumber>1</TrackNumber>
    <FloorNumber>28</FloorNumber>
    <X>5.65546</X>
    <Y>2</Y>
    <Z>6.823557</Z>
  </Track>
  <Track>
    <FloorName>EndFloor</FloorName>
    <TrackNumber>1</TrackNumber>
    <FloorNumber>-1</FloorNumber>
    <X>3.810757</X>
    <Y>2</Y>
    <Z>3.427184</Z>
  </Track>
</TrackInfo>